{
  "main": {
      "title": "Develop • Deploy • Deliver",
      "paragraph": "One Platform provides a fast way to develop, deploy and deliver application to your users.",
      "stats": [
          {
              "title": "Apps Deployed",
              "value": "26+"
          },
          {
              "title": "Deployments/month",
              "value": "750+"
          },
          {
              "title": "Avg. time to deploy",
              "value": "2.5min"
          },
          {
              "title": "Avg. time saved",
              "value": "11hours 38min"
          }
      ]
  }
}
